[
    {
        "name": "Ez2Lazer",
        "versions": [
            {
                "version": "2026-4-4",
                "release_date": "2026-04-04T12:27:33Z",
                "hashes": {
                    "0b934e5f7d897702151fd216d2585574": "Windows"
                }
            },
            {
                "version": "2026-3-27",
                "release_date": "2026-03-27T15:29:05Z",
                "hashes": {
                    "43c82efa943777fbf470152827a9ca04": "Windows",
                    "7de369f55ed1e64965cef856e3ea79e1": "Windows Debug Build"
                }
            },
            {
                "version": "2026-3-18",
                "release_date": "2026-03-17T16:11:54Z",
                "hashes": {
                    "176a7f56149492d8c7754e07583b19fc": "Windows",
                    "8b7604da6dd64c963fef58dd1019d14a": "Windows Debug Build"
                }
            },
            {
                "version": "2026-3-14",
                "release_date": "2026-03-14T05:50:01Z",
                "hashes": {
                    "34a20f9a8281e97a4cee9274a418d613": "Windows",
                    "208ec173440f73f58948213dead2553d": "Windows Debug Build"
                }
            },
            {
                "version": "2026-3-5",
                "release_date": "2026-03-05T15:57:25Z",
                "hashes": {
                    "bb697a445689c8c3e1dce15f1d2d1e21": "Windows",
                    "3424ff1c4549567b16610ea7140a85b6": "Windows Debug Build"
                }
            }
        ]
    }
]